pytest_exceptional
